peopleprinter/__init__.py
peopleprinter/main.py
peopleprinter/manufacturers/__init__.py
peopleprinter/manufacturers/HP/__init__.py
peopleprinter/manufacturers/HP/major_hp.py
peopleprinter/manufacturers/KYOCERA/__init__.py
peopleprinter/manufacturers/KYOCERA/kyocera_3040.py
peopleprinter/manufacturers/KYOCERA/major_kyocera.py
peopleprinter/manufacturers/PANTUM/__init__.py
peopleprinter/manufacturers/PANTUM/major_pantum.py
peopleprinter/manufacturers/Xerox/__init__.py
peopleprinter/manufacturers/Xerox/major_xerox.py
peopleprinter/src/__init__.py
peopleprinter-0.0.9.dist-info/METADATA
peopleprinter-0.0.9.dist-info/WHEEL
peopleprinter-0.0.9.dist-info/top_level.txt
peopleprinter-0.0.9.dist-info/RECORD
