Metadata-Version: 2.1
Name: peopleprinter
Version: 0.0.9
Summary: Parsing printers
Author-email: Guazah <guazah@gmail.com>
Project-URL: Homepage, https://github.com/Forsunkin/PeoplePrinter
Project-URL: Bug Tracker, https://github.com/Forsunkin/PeoplePrinter
Classifier: Programming Language :: Python :: 3
Classifier: License :: OSI Approved :: MIT License
Classifier: Operating System :: OS Independent
Requires-Python: >=3.7
